neon_phal_plugin_switches/__init__.py
neon_phal_plugin_switches-0.0.6.dist-info/LICENSE.md
neon_phal_plugin_switches-0.0.6.dist-info/METADATA
neon_phal_plugin_switches-0.0.6.dist-info/WHEEL
neon_phal_plugin_switches-0.0.6.dist-info/entry_points.txt
neon_phal_plugin_switches-0.0.6.dist-info/top_level.txt
neon_phal_plugin_switches-0.0.6.dist-info/RECORD
